odoo/addons/pos_product_label/README.rst
odoo/addons/pos_product_label/__init__.py
odoo/addons/pos_product_label/__manifest__.py
odoo/addons/pos_product_label/i18n/es.po
odoo/addons/pos_product_label/i18n/it.po
odoo/addons/pos_product_label/i18n/pos_product_label.pot
odoo/addons/pos_product_label/models/__init__.py
odoo/addons/pos_product_label/models/pos_config.py
odoo/addons/pos_product_label/models/pos_session.py
odoo/addons/pos_product_label/models/res_config_settings.py
odoo/addons/pos_product_label/readme/CONTRIBUTORS.rst
odoo/addons/pos_product_label/readme/DESCRIPTION.rst
odoo/addons/pos_product_label/readme/USAGE.rst
odoo/addons/pos_product_label/static/description/icon.png
odoo/addons/pos_product_label/static/description/index.html
odoo/addons/pos_product_label/static/description/preview.png
odoo/addons/pos_product_label/static/src/PrintLabelButton.esm.js
odoo/addons/pos_product_label/static/src/PrintLabelButton.xml
odoo/addons/pos_product_label/static/src/PrintLabelPopup.esm.js
odoo/addons/pos_product_label/static/src/PrintLabelPopup.scss
odoo/addons/pos_product_label/static/src/PrintLabelPopup.xml
odoo/addons/pos_product_label/views/res_config_settings.xml
odoo/addons/pos_product_label/wizards/__init__.py
odoo/addons/pos_product_label/wizards/product_label_layout.py
odoo_addon_pos_product_label-16.0.1.0.2.2.dist-info/METADATA
odoo_addon_pos_product_label-16.0.1.0.2.2.dist-info/WHEEL
odoo_addon_pos_product_label-16.0.1.0.2.2.dist-info/top_level.txt
odoo_addon_pos_product_label-16.0.1.0.2.2.dist-info/RECORD
